{
  "gametitle":"Принцесса Луна против тортиков",
  "menustart":"Начать",
  "menudiff":"Сложность",
  "menuhelp":"Справка",
  "menuctrl":"Управление",
  "menusound":"Звуки",
  "menumusic":"Музыка",
  "menufullscreen":"Полный экран",
  "menulang":"Язык",
  "menuexit":"Выход",
  "menurestart":"Заново",
  "menuback":"Назад",
  "menudefault":"По умолчанию",
  "text_win":"Победа!",
  "text_fail":"Поражение!",
  "text_on":"Вкл",
  "text_off":"Выкл",
  "text_hard":"Высокая",
  "text_medi":"Средняя",
  "text_easy":"Низкая",
  "text_lcm":"ЛКМ",
  "text_mcm":"СКМ",
  "text_rcm":"ПКМ",
  "action_switch":"Следующее действие",
  "action_apply":"Применить действие",
  "action_sel_teleport":"Выбор телепорта",
  "action_sel_laser":"Выбор лазера",
  "action_sel_chicken":"Выбор курицы",
  "action_sel_shield":"Выбор щита",
  "action_left":"Движение влево",
  "action_right":"Движение вправо",
  "msg_laserfail":"Селестия поражена роголазером",
  "msg_cakeover":"Все кексики уничтожены",
  "msg_celestiafail":"Селестия переела кексов"
}
